hierarchicalforecast/__init__.py
hierarchicalforecast/core.py
hierarchicalforecast/evaluation.py
hierarchicalforecast/methods.py
hierarchicalforecast/probabilistic_methods.py
hierarchicalforecast/utils.py
hierarchicalforecast-1.3.1.dist-info/licenses/LICENSE
hierarchicalforecast-1.3.1.dist-info/METADATA
hierarchicalforecast-1.3.1.dist-info/WHEEL
hierarchicalforecast-1.3.1.dist-info/top_level.txt
hierarchicalforecast-1.3.1.dist-info/RECORD
