Metadata-Version: 2.4
Name: hierarchicalforecast
Version: 1.3.1
Summary: Hierarchical Methods Time series forecasting
Author-email: Nixtla <business@nixtla.io>
License: Apache Software License 2.0
Project-URL: Homepage, https://github.com/Nixtla/hierarchicalforecast/
Project-URL: Repository, https://github.com/Nixtla/hierarchicalforecast/
Project-URL: Documentation, https://nixtlaverse.nixtla.io/hierarchicalforecast/
Keywords: time-series,forecasting,datasets,hierarchical
Classifier: Development Status :: 2 - Pre-Alpha
Classifier: Intended Audience :: Developers
Classifier: Natural Language :: English
Classifier: License :: OSI Approved :: Apache Software License
Classifier: Programming Language :: Python :: 3.9
Classifier: Programming Language :: Python :: 3.10
Classifier: Programming Language :: Python :: 3.11
Classifier: Programming Language :: Python :: 3.12
Classifier: Programming Language :: Python :: 3.13
Requires-Python: >=3.9
License-File: LICENSE
Requires-Dist: numpy
Requires-Dist: numba
Requires-Dist: pandas>=2.1.0
Requires-Dist: scikit-learn>=1.2
Requires-Dist: matplotlib
Requires-Dist: narwhals>=2.0
Requires-Dist: qpsolvers[clarabel]
Requires-Dist: utilsforecast>=0.2.12
Requires-Dist: intel-cmplr-lib-rt; platform_system != "Darwin" and platform_machine == "x86_64"
Provides-Extra: dev
Requires-Dist: datasetsforecast; extra == "dev"
Requires-Dist: fire; extra == "dev"
Requires-Dist: ipython<=8.32.0; extra == "dev"
Requires-Dist: statsforecast>=1.0.0; extra == "dev"
Requires-Dist: requests; extra == "dev"
Requires-Dist: scipy; extra == "dev"
Requires-Dist: pre-commit; extra == "dev"
Requires-Dist: ruff; extra == "dev"
Requires-Dist: black; extra == "dev"
Requires-Dist: pytest; extra == "dev"
Requires-Dist: pytest-benchmark; extra == "dev"
Requires-Dist: pytest-cov; extra == "dev"
Requires-Dist: pip-licenses; extra == "dev"
Provides-Extra: polars
Requires-Dist: polars[numpy]<=1.32.0; extra == "polars"
Dynamic: license-file
